Workbook

Sheet Capital Structure
B6: Weighted average cost of capital
B8: All figures are in USD (mn)
B10: Peer Comps
G11: Debt / | H11: Debt / | I11: Levered | J11: Unlevered
B12: Name of the Comp | C12: Country | D12: Total Debt | E12: Total Equity | F12: Tax Rate 1 | G12: Equity | H12: Capital | I12: Beta 2 | J12: Beta 3
B14: Tesla | C14: United States | D14: 14719000 | E14: 32155000 | F14: 0.27 | G14: =E14/D14 -> 2.1845913 | H14: =D14/E14 -> 0.45775152 | I14: 1.83 | J14: =I14/(1+(1-0.21)*G14) -> 0.67135585

Sheet Raw Data
B2: Metric | C2: Value | D2: Source | E2: Formula
B3: Company Name | C3: Tesla Inc.
B4: Ticker | C4: TSLA
B5: Market Capitalization (E) | C5: 32155000 | D5: Yahoo Finance
B6: Market Value of Debt (D) | C6: 14719000 | D6: Yahoo Finance
B7: Total Value | C7: 46874000
B8: Risk-Free Rate | C8: 4.30% | D8: Yahoo Finance
B9: Market Risk Premium | C9: 5.50% | D9: Yahoo Finance
B10: Levered Beta | C10: 1.83 | D10: Yahoo Finance
B11: Tax Rate | C11: 27.00% | D11: Yahoo Finance
B12: Interest Expense | C12: 334000 | D12: Yahoo Finance
B13: Total Debt | C13: 14719 | D13: Yahoo Finance
B14: Pre-tax Cost of Debt | C14: 2.08% | D14: Yahoo Finance
B15: Shares Outstanding | C15: 3752.43 | D15: Yahoo Finance
B16: Current Share Price | C16: 318.23 USD | D16: Yahoo Finance
B17: Enterprise Value | C17: 1194135.8 million | D17: Yahoo Finance | E17: Outstanding shares * Current share price

Sheet Cost Of Equity 
B2: Input | C2: Value
B3: Risk-Free Rate | C3: 4.30%
B4: Levered Beta | C4: 1.83
B5: Market Risk Premium | C5: 5.50%
B6: Cost of Equity | C6: =C3+C4*(C5) -> 0.14365

Sheet Cost Of Debt 
B2: Input | C2: Value | D2: Formula/Notes
B3: Interest Expense | C3: 334000
B4: Total Debt | C4: 14719000
B5: Cost of Debt | C5: =C3/C4 -> 0.022691759 | D5: Interest exp/ Total debt
B6: Tax Expense | C6: 135300
B7: Pre-tax Cost of Debt | C7: 5217000
B8: Effective Tax Rate | C8: =C6/C7 -> 0.025934445 | D8: Tax Expense/ Effective tax Rate
B9: After-tax Cost of Debt | C9: =C5*(1-C8) -> 0.022103261 | D9: Cost of Debt* (1-Effective Tax Rate)

Sheet WACC
B2: Component | C2: Value | D2: Formula
B3: Weight of Equity (E/V) | C3: 0.6859 | D3: Total Equity / Total Value
B4: Weight of Debt (D/V) | C4: 0.314 | D4: Total Debt / Total Value
B5: Cost of Equity (Re) | C5: ='Cost Of Equity '!C6 -> 0.14365
B6: After-tax Cost of Debt (Rd) | C6: ='Cost Of Debt '!C5 -> 0.022691759
B7: Tax Rate | C7: 0.27
B8: WACC | C8: =(C3*C5)+(C4*C6*(1-C7)) -> 0.10373094 | D8: (EquityWeight*Re)+(DebtWeight*Rd*(1-TaxRate))

Sheet Sensitivity Analysis
B2: Assume a ±10% change in WACC
B3: Assume a ±10% change in beta
B5: Scenario | C5: WACC | D5: Enterprise Value | E5: Equity Value | F5: Share Price | J5: Calculations
B6: Base Case | C6: 0.1037 | D6: 1194135.8 | E6: 1179416.8 | F6: =E6/'Raw Data'!C15 -> 314.30748
B7: Low WACC (-1) | C7: =C6-0.01 -> 0.0937 | D7: =D6*1.1 -> 1313549.4 | E7: =D7-'Raw Data'!C13 -> 1298830.4 | F7: =E7/'Raw Data'!C15 -> 346.13048 | J7: 1. Low WACC Scenario | K7: 1. Low WACC Scenario:
B8: High WACC (+1) | C8: =C6+0.01 -> 0.1137 | D8: =D6*0.9 -> 1074722.2 | E8: =D8-'Raw Data'!C13 -> 1060003.2 | F8: =E8/'Raw Data'!C15 -> 282.48448 | K8: Base EV = 1,194,135.8
K9: Increase by 10%
B10: Scenario | C10: Change Beta | D10: Changes in COE | E10: New WACC | K10: EV=1,194,135.8×1.10
B11: Low Beta | C11: ='Capital Structure'!I14*0.9 -> 1.647 | D11: ='Raw Data'!C8+C11*'Raw Data'!C9 -> 0.133585 | E11: =(WACC!C3*D11)+(WACC!C4*WACC!C6*(1-WACC!C7)) -> 0.096827356 | K11: = 1,313,549.4
B12: High Beta | C12: ='Capital Structure'!I14*1.1 -> 2.013 | D12: ='Raw Data'!C8+'Sensitivity Analysis'!C12*'Raw Data'!C9 -> 0.153715 | E12: =(WACC!C3*D12)+(WACC!C4*WACC!C6*(1-WACC!C7)) -> 0.11063452 | K12: Equity Value= EV - Total debt
K13: 1,313,549.4−14,719=1,298,830.4
K14: Share Price:
K15: 1,298,830.4/3,752.43
K16: ​=350.05
