Workbook

Sheet FCF
C2: DCF Valuation of Tesla Company
B5: Free Cash Flow (FCF) Calculation
B6: Particulars | C6: 2024 | D6: =C6+1 -> 2025 | E6: =D6+1 -> 2026 | F6: =E6+1 -> 2027 | G6: =F6+1 -> 2028 | H6: =G6+1 -> 2029
B7: Revenue | C7: =D20 -> 97690000 | D7: =E20 -> 94827000 | E7: =F20 -> 1.043097e+08 | F7: =G20 -> 1.1474067e+08 | G7: =H20 -> 1.2850955e+08 | H7: =I20 -> 1.4778598e+08
B8: EBIT Margin | C8: =D27/C7 -> 0.01200737 | D8: =E27/D7 -> 0.0068809516 | E8: =F27/E7 -> 0.0063911892 | F8: =G27/F7 -> 0.0070052261 | G8: =H27/G7 -> 0.0078111494 | H8: =I27/H7 -> 0.0088623538
B9: EBIT | C9: =D27 -> 1173000 | D9: =E27 -> 652500 | E9: =F27 -> 666663.03 | F9: =G27 -> 803784.33 | G9: =H27 -> 1003807.3 | H9: =I27 -> 1309731.7
B10: Tax | C10: =D28 -> 293250 | D10: =E28 -> 163125 | E10: =F28 -> 166665.76 | F10: =G28 -> 200946.08 | G10: =H28 -> 250951.83 | H10: =I28 -> 327432.92
B11: D&A | C11: =D25 -> 5368000 | D11: =E25 -> 2854500 | E11: =F25 -> 6269013 | F11: =G25 -> 6895914.3 | G11: =H25 -> 7723424 | H11: =I25 -> 8881937.6
B12: CapEx | C12: -11342000 | D12: -8527000 | E12: -12930000 | F12: =E12*(1+0.05) -> -13576500 | G12: =F12*(1+0.05) -> -14255325 | H12: =G12*(1+0.05) -> -14968091
B13: Non-Cash Working Capital inc/dec | C13: =E47 -> 3171000 | D13: =E48 -> 3202000 | E13: =D13*(1+0.05) -> 3362100 | F13: =E13*(1+0.05) -> 3530205 | G13: =F13*(1+0.05) -> 3706715.2 | H13: =G13*(1+0.05) -> 3892051
B14: Free Cash Flow (FCF) | C14: =C9-(SUM(C10,C11,C12,C13)) -> 3682750 | D14: =D9-(SUM(D10,D11,D12,D13)) -> 2959875 | E14: =E9-(SUM(E10,E11,E12,E13)) -> 3798884.3 | F14: =F9-(SUM(F10,F11,F12,F13)) -> 3753219 | G14: =G9-(SUM(G10,G11,G12,G13)) -> 3578041.2 | H14: =H9-(SUM(H10,H11,H12,H13)) -> 3176401.4
B16: TESLA
D17: 2024 | E17: =D17+1 -> 2025 | F17: =E17+1 -> 2026 | G17: =F17+1 -> 2027 | H17: =G17+1 -> 2028 | I17: =H17+1 -> 2029
A19: # | B19: ="Income Statement"&" - "&B16 -> Income Statement - TESLA
B20: Revenue | D20: 97690000 | E20: 94827000 | F20: =E20*(1+F32) -> 1.043097e+08 | G20: =F20*(1+G32) -> 1.1474067e+08 | H20: =G20*(1+H32) -> 1.2850955e+08 | I20: =H20*(1+I32) -> 1.4778598e+08
B21: COGS | D21: 80240000 | E21: 77733000 | F21: =F20*F33 -> 83447760 | G21: =G20*G33 -> 91792536 | H21: =H20*H33 -> 1.0280764e+08 | I21: =I20*I33 -> 1.1822879e+08
B22: Gross Profit | D22: =D20-D21 -> 17450000 | E22: =E20-E21 -> 17094000 | F22: =F20-F21 -> 20861940 | G22: =G20-G21 -> 22948134 | H22: =H20-H21 -> 25701910 | I22: =I20-I21 -> 29557197
B23: Selling & Adm Expences | D23: 9690000 | E23: 12245000 | F23: =F20*F34 -> 12517164 | G23: =G20*G34 -> 13768880 | H23: =H20*H34 -> 15421146 | I23: =I20*I34 -> 17734318
B24: EBITDA | D24: =D22-D23 -> 7760000 | E24: =E22-E23 -> 4849000 | F24: =F22-F23 -> 8344776 | G24: =G22-G23 -> 9179253.6 | H24: =H22-H23 -> 10280764 | I24: =I22-I23 -> 11822879 | L24: =E26/D26 -> 1.1009024
B25: Depreciation | D25: 5368000 | E25: 2854500 | F25: =F20*F35 -> 6269013 | G25: =G20*G35 -> 6895914.3 | H25: =H20*H35 -> 7723424 | I25: =I20*I35 -> 8881937.6
B26: Intrest | D26: 1219000 | E26: 1342000 | F26: =E26*F36 -> 1409100 | G26: =F26*G36 -> 1479555 | H26: =G26*H36 -> 1553532.8 | I26: =H26*I36 -> 1631209.4
B27: EBT | D27: =D24-SUM(D25,D26) -> 1173000 | E27: =E24-SUM(E25,E26) -> 652500 | F27: =F24-SUM(F25,F26) -> 666663.03 | G27: =G24-SUM(G25,G26) -> 803784.33 | H27: =H24-SUM(H25,H26) -> 1003807.3 | I27: =I24-SUM(I25,I26) -> 1309731.7
B28: Taxes | D28: =D27*D37 -> 293250 | E28: =E27*E37 -> 163125 | F28: =F27*F37 -> 166665.76 | G28: =G27*G37 -> 200946.08 | H28: =H27*H37 -> 250951.83 | I28: =I27*I37 -> 327432.92
B29: Net Income | D29: =D27-D28 -> 879750 | E29: =E27-E28 -> 489375 | F29: =F27-F28 -> 499997.27 | G29: =G27-G28 -> 602838.25 | H29: =H27-H28 -> 752855.48 | I29: =I27-I28 -> 982298.76
A31: # | B31: ="Assumption Drivers"&" - "&B16 -> Assumption Drivers - TESLA
B32: Revenue Growth | D32: NA | E32: =E20/D20-1 -> -0.029306992 | F32: 0.1 | G32: =F32 -> 0.1 | H32: 0.12 | I32: 0.15
B33: COGS% of Revenue | D33: =D21/D20 -> 0.82137373 | E33: =E20/D20 -> 0.97069301 | F33: 0.8 | G33: 0.8 | H33: =G33 -> 0.8 | I33: =H33 -> 0.8
B34: Selling & Adm Expences | D34: 0.12 | E34: 0.12 | F34: 0.12 | G34: 0.12 | H34: 0.12 | I34: 0.12
B35: Depreciation % of Sales | D35: =D25/D20 -> 0.05494933 | E35: =E25/E20 -> 0.030102186 | F35: 0.0601 | G35: 0.0601 | H35: 0.0601 | I35: 0.0601
B36: Interest | E36: 1.05 | F36: 1.05 | G36: 1.05 | H36: 1.05 | I36: 1.05
B37: Taxes | D37: 0.25 | E37: 0.25 | F37: 0.25 | G37: 0.25 | H37: 0.25 | I37: 0.25
C47: =48390000-17626000 -> 30764000 | E47: =4418000+12017000+5362000-17626000-1000000 -> 3171000
E48: =4576000+12392000+7615000-19449000-1932000 -> 3202000

Sheet WACC
B2: Weighted Average Cost of Capital (WACC)
B3: Cost of Equity
B4: Risk-Free Rate | C4: 4.30%
B5: Beta | C5: 1.83
B6: Equity Risk Premium | C6: 0.055
B7: Cost of Equity (Ke = Rf + Beta × ERP) | C7: =C4+C5*(C6) -> 0.14365
B9: Cost of Debt
B10: Pre-Tax Cost of Debt | C10: 5217000
B11: Tax Rate | C11: 0.27
B12: After-Tax Cost of Debt | C12: 0.022103261
B14: Capital Structure
B15: Market Value of Equity
B16: Market Value of Debt | C16: 14719000
B17: Market value of Equity | C17: 32155000
B18: Total Capital | C18: 46874000
B19: Equity Weight | C19: =C17/C18 -> 0.68598797
B20: Debt Weight | C20: =C16/C18 -> 0.31401203
B21: WACC | C21: =(C19*C7)+(C20*C12*(1-C11)) -> 0.10360888

Sheet Terminal Value
B2: Terminal Value Calculation
B3: EV/EBITDA Multiple | C3: 0.04
B4: Terminal Growth Rate | C4: 0.03
B5: WACC | C5: =WACC!C21 -> 0.10360888
B8: Year | C8: =FCF!D17 -> 2024 | D8: =FCF!E17 -> 2025 | E8: 2026E | F8: 2027E | G8: 2028E | H8: 2029E
B9: EBITDA | C9: =FCF!D24 -> 7760000 | D9: =FCF!E24 -> 4849000 | E9: =FCF!F24 -> 8344776 | F9: =FCF!G24 -> 9179253.6 | G9: =FCF!H24 -> 10280764 | H9: =FCF!I24 -> 11822879
B10: FCF | C10: =FCF!C14 -> 3682750 | D10: =FCF!D14 -> 2959875 | E10: =FCF!E14 -> 3798884.3 | F10: =FCF!F14 -> 3753219 | G10: =FCF!G14 -> 3578041.2 | H10: =FCF!H14 -> 3176401.4
F14: Perpertuity Growth TV | H14: =H10*(1+C4)/(C5-C4) -> 44446997
F15: EV/EBITDA TV | H15: =H9*C3 -> 472915.15
F16: Average | H16: =AVERAGE(H14:H15) -> 22459956

Sheet Discounting
B2: Discounted Cash Flow
B4: WACC | C4: =WACC!C21 -> 0.10360888
B6: Particulars | C6: Year 1 | D6: Year 2 | E6: Year 3 | F6: Year 4 | G6: Year 5 | H6: Year 6 | I6: Terminal Value
B7: FCF | C7: =FCF!C14 -> 3682750 | D7: =FCF!D14 -> 2959875 | E7: =FCF!E14 -> 3798884.3 | F7: =FCF!F14 -> 3753219 | G7: =FCF!G14 -> 3578041.2 | H7: =FCF!H14 -> 3176401.4 | I7: ='Terminal Value'!H14 -> 44446997
B8: Discount Period | C8: 1 | D8: 2 | E8: 3 | F8: 4 | G8: 5 | H8: 6 | I8: 6
B9: Discount Factor | C9: =1/(1+$C$4)^C8 -> 0.90611812 | D9: =1/(1+$C$4)^D8 -> 0.82105005 | E9: =1/(1+$C$4)^E8 -> 0.74396833 | F9: =1/(1+$C$4)^F8 -> 0.67412318 | G9: =1/(1+$C$4)^G8 -> 0.61083523 | H9: =1/(1+$C$4)^H8 -> 0.55348887 | I9: =1/(1+$C$4)^I8 -> 0.55348887
B10: Present Value | C10: =C7*C9 -> 3337006.5 | D10: =D7*D9 -> 2430205.5 | E10: =E7*E9 -> 2826249.6 | F10: =F7*F9 -> 2530131.9 | G10: =G7*G9 -> 2185593.7 | H10: =H7*H9 -> 1758102.8 | I10: =I7*I9 -> 24600918
B12: Enterprise Value | C12: =SUM(C10:I10) -> 39668208

Sheet EV to Equity Value
B2: Enterprise Value to Equity Value
B3: Enterprise Value | C3: =SUM(Discounting!C10:I10) -> 39668208
B4: Less: Total Debt | C4: -14719000
B5: Add: Cash & Cash Equivalents | C5: 44059000
B6: Equity Value | C6: =SUM(C3:C5) -> 69008208
B7: Shares Outstanding (Million) | C7: 375100
B8: Intrinsic Value Per Share | C8: =C6/C7 -> 183.97283
B9: Current Market Price | C9: 332
B10: Upside / (Downside) | C10: =C8/C9-1 -> -0.44586497

Sheet FULL DCF
B3: Discounted Cash Flow Full
B5: Assumptions pt1 | E5: Assumptions pt2
B6: Growth rate | C6: ='Terminal Value'!C4 -> 0.03 | E6: Beta | F6: =WACC!C5 -> 1.83
B7: EV/EBITDA Multiple | C7: 4 | E7: Market Return | F7: 0.1
B8: Cost of Debt | C8: 0.0221 | E8: Equity value | F8: =WACC!C17 -> 32155000
B9: Tax Rate | C9: 0.27 | E9: Debt value | F9: =WACC!C16 -> 14719000
B10: 10y Treasury | C10: 0.015
B13: Year | D13: =FCF!D17 -> 2024 | E13: =FCF!E17 -> 2025 | F13: =FCF!F17 -> 2026 | G13: =FCF!G17 -> 2027 | H13: =FCF!H17 -> 2028 | I13: =FCF!I17 -> 2029
B15: Free Cash Flows
B16: EBIT | D16: =FCF!C9 -> 1173000 | E16: =FCF!D9 -> 652500 | F16: =FCF!E9 -> 666663.03 | G16: =FCF!F9 -> 803784.33 | H16: =FCF!G9 -> 1003807.3 | I16: =FCF!H9 -> 1309731.7
B17: Tax | D17: =FCF!C10 -> 293250 | E17: =FCF!D10 -> 163125 | F17: =FCF!E10 -> 166665.76 | G17: =FCF!F10 -> 200946.08 | H17: =FCF!G10 -> 250951.83 | I17: =FCF!H10 -> 327432.92
B18: D&A | D18: =FCF!C11 -> 5368000 | E18: =FCF!D11 -> 2854500 | F18: =FCF!E11 -> 6269013 | G18: =FCF!F11 -> 6895914.3 | H18: =FCF!G11 -> 7723424 | I18: =FCF!H11 -> 8881937.6
B19: CapEx | D19: =FCF!C12 -> -11342000 | E19: =FCF!D12 -> -8527000 | F19: =FCF!E12 -> -12930000 | G19: =FCF!F12 -> -13576500 | H19: =FCF!G12 -> -14255325 | I19: =FCF!H12 -> -14968091
B20: Non-cash Work. Capital (inc) / dec | D20: =FCF!C13 -> 3171000 | E20: =FCF!D13 -> 3202000 | F20: =FCF!E13 -> 3362100 | G20: =FCF!F13 -> 3530205 | H20: =FCF!G13 -> 3706715.2 | I20: =FCF!H13 -> 3892051
B21: Free Cash Flow | D21: =FCF!C14 -> 3682750 | E21: =FCF!D14 -> 2959875 | F21: =FCF!E14 -> 3798884.3 | G21: =FCF!F14 -> 3753219 | H21: =FCF!G14 -> 3578041.2 | I21: =FCF!H14 -> 3176401.4
B23: WACC
B24: Cost of Equity | C24: =WACC!C7 -> 0.14365
B25: D/D+E | C25: =WACC!C20 -> 0.31401203
B26: E/D+E | C26: =WACC!C19 -> 0.68598797
B27: WACC | C27: =(C26*C24)+(C25*C8*(1-C9)) -> 0.10360813
B29: Terminal Value
B30: EBITDA | I30: ='Terminal Value'!H9 -> 11822879
B31: EV/EBITDA | I31: =I30*$C$7 -> 47291515
B32: Perpetuity Growth | I32: ='Terminal Value'!H10*(1+'Terminal Value'!$C$4)/('Terminal Value'!$C$5-'Terminal Value'!$C$4) -> 44446997
B33: Average | I33: ='Terminal Value'!H16 -> 22459956
B35: Discounting
B36: Discount Factor | D36: =Discounting!C9 -> 0.90611812 | E36: =Discounting!D9 -> 0.82105005 | F36: =Discounting!E9 -> 0.74396833 | G36: =Discounting!F9 -> 0.67412318 | H36: =Discounting!G9 -> 0.61083523 | I36: =Discounting!I9 -> 0.55348887
B37: PV of FCF | D37: =D36*D21 -> 3337006.5 | E37: =E36*E21 -> 2430205.5 | F37: =F36*F21 -> 2826249.6 | G37: =G36*G21 -> 2530131.9 | H37: =H36*H21 -> 2185593.7
B38: PV of TV | I38: =I36*I21 -> 1758102.8
B39: Enterprise Value | I39: =Discounting!C12 -> 39668208
B41: Enterprise Value to Equity Value
B42: Cash | C42: ='EV to Equity Value'!C5 -> 44059000
B43: Total Debt | C43: ='EV to Equity Value'!C4 -> -14719000
B44: Equity Value | C44: =I39+C42+C43 -> 69008208
B46: Shares Outstanding | C46: ='EV to Equity Value'!C7 -> 375100
B47: Implied Share Price | C47: =C44/C46 -> 183.97283
