Workbook

Sheet HUL_Financials
A1: Financial Year | B1: Revenue | C1: COGS | D1: Gross Profit | E1: EBITDA | F1: EBIT | G1: Net Profit | H1: EPS | I1: Dividend
A2: FY2021 | B2: 47028 | C2: 25301 | D2: 21727 | E2: 11626 | F2: 10435 | G2: 7829 | H2: 33.320565 | I2: 40.506895
A3: FY2022 | B3: 52446 | C3: 29066 | D3: 23380 | E3: 12857 | F3: 11660 | G3: 8673 | H3: 36.912666 | I3: 34.005788
A4: FY2023 | B4: 60580 | C4: 35381 | D4: 25199 | E4: 14147 | F4: 12896 | G4: 9695 | H4: 41.262343 | I4: 39.006639
A5: FY2024 | B5: 61896 | C5: 33651 | D5: 28245 | E5: 14659 | F5: 13109 | G5: 9465 | H5: 40.283453 | I5: 42.00715
A6: FY2025 | B6: 61328 | C6: 33519 | D6: 27809 | E6: 14698 | F6: 13064 | G6: 9316 | H6: 39.649302 | I6: 53.009023
A7: FY2026 | B7: 64468 | C7: 35634 | D7: 28834 | E7: 15039 | F7: 13296 | G7: 10136 | H7: 43.139258 | I7: 41.00698

Sheet HUL_BalanceSheet
A1: Financial Year | B1: Total Assets | C1: Current Assets | D1: Non-Current Assets | E1: Cash | F1: Inventory | G1: Equity | H1: Total Debt | I1: Current Liabilities | J1: Non-Current Liabilities
A2: FY2021 | B2: 68740 | C2: 9808 | D2: 58932 | E2: 4471 | F2: 3579 | G2: 235 | H2: =SUM(I2,J2) -> 21066 | I2: 21066 | J2: 0
A3: FY2022 | B3: 70506 | C3: 10178 | D3: 60328 | E3: 3846 | F3: 4096 | G3: 235 | H3: =SUM(I3,J3) -> 21445 | I3: 20402 | J3: 1043
A4: FY2023 | B4: 73077 | C4: 12008 | D4: 61069 | E4: 4678 | F4: 4251 | G4: 235 | H4: =SUM(I4,J4) -> 22773 | I4: 21554 | J4: 1219
A5: FY2024 | B5: 78489 | C5: 14578 | D5: 63911 | E5: 7559 | F5: 4022 | G5: 235 | H5: =SUM(I5,J5) -> 27271 | I5: 25787 | J5: 1484
A6: FY2025 | B6: 79863 | C6: 15788 | D6: 64075 | E6: 7554 | F6: 4415 | G6: 235 | H6: =SUM(I6,J6) -> 30461 | I6: 28813 | J6: 1648
A7: FY2026 | B7: 79738 | C7: 11416 | D7: 68322 | E7: 3248 | F7: 4789 | G7: 235 | H7: =SUM(I7,J7) -> 30999 | I7: 29521 | J7: 1478

Sheet HUL_CashFlow
A1: Financial Year | B1: Operating Cash Flow | C1: Investing Cash Flow | D1: Financing Cash Flow | E1: Capital Expenditure | F1: Free Cash Flow
A2: FY2021 | B2: 8040 | C2: 1791 | D2: -6819 | E2: -862 | F2: 3012
A3: FY2022 | B3: 9063 | C3: -1228 | D3: -9309 | E3: -4163 | F3: -1474
A4: FY2023 | B4: 8045 | C4: -1728 | D4: -8015 | E4: -1228 | F4: -1698
A5: FY2024 | B5: 9031 | C5: -1484 | D5: -8953 | E5: -1192 | F5: -1406
A6: FY2025 | B6: 16782 | C6: -5324 | D6: -10034 | E6: -1477 | F6: 1424
A7: FY2026 | B7: 11098 | C7: 6473 | D7: -13101 | E7: -1275 | F7: 4470

Sheet Nestle_Financials
A1: Financial Year | B1: Revenue | C1: COGS | D1: Gross Profit | E1: EBITDA | F1: EBIT | G1: Net Profit | H1: EPS | I1: Dividend
A2: FY2021 | B2: 14740.59 | C2: 8521.15 | D2: 6219.44 | E2: 3562.4 | F2: 2969.7 | G2: 2230.79 | H2: 11.570488 | I2: 10.002075
A3: FY2022 | B3: 16896.96 | C3: 10221.7 | D3: 6675.26 | E3: 3706.29 | F3: 3148.71 | G3: 2283.26 | H3: 11.842635 | I3: 11.002282
A4: FY2023 | B4: 19126.3 | C4: 10281.89 | D4: 8844.41 | E4: 4470.99 | F4: 3922.79 | G4: 2883.17 | H4: 14.954201 | I4: 8.7018154
A5: FY2024 | B5: 24393.89 | C5: 14101.72 | D5: 10292.17 | E5: 5843.12 | F5: 5129.88 | G5: 3773.85 | H5: 19.570866 | I5: 16.100814
A6: FY2025 | B6: 20201.56 | C6: 11692.86 | D6: 8508.7 | E6: 4771.33 | F6: 4095.41 | G6: 2962.44 | H6: 15.362962 | I6: 13.5007
A7: FY2026 | B7: 23154.6 | C7: 13627.64 | D7: 9526.96 | E7: 5306.96 | F7: 4449.42 | G7: 3384.37 | H7: 17.551055 | I7: 12

Sheet Nestle_BalanceSheet
A1: Financial Year | B1: Total Assets | C1: Current Assets | D1: Non-Current Assets | E1: Cash | F1: Inventory | G1: Equity | H1: Total Debt | I1: Current Liabilities | J1: Non-Current Liabilities
A2: FY2021 | B2: 8234.13 | C2: 2494.03 | D2: 5740.1 | E2: 735.41 | F2: 1592.65 | G2: 96.42 | H2: =SUM(I2,J2) -> 6287.75 | I2: 6021.29 | J2: 266.46
A3: FY2022 | B3: 8978.74 | C3: 3066.21 | D3: 5912.53 | E3: 945.55 | F3: 1928.77 | G3: 96.42 | H3: =SUM(I3,J3) -> 6519.57 | I3: 6249.05 | J3: 270.52
A4: FY2023 | B4: 8978.74 | C4: 3066.21 | D4: 5912.53 | E4: 945.55 | F4: 1928.77 | G4: 96.42 | H4: =SUM(I4,J4) -> 6519.57 | I4: 6249.05 | J4: 270.52
A5: FY2024 | B5: 10523.06 | C5: 3168.67 | D5: 7354.39 | E5: 778.85 | F5: 2089.36 | G5: 96.42 | H5: =SUM(I5,J5) -> 7182.17 | I5: 6837.64 | J5: 344.53
A6: FY2025 | B6: 12323.89 | C6: 3308.94 | D6: 9014.95 | E6: 95.65 | F6: 2850.14 | G6: 96.42 | H6: =SUM(I6,J6) -> 8206.74 | I6: 7039.89 | J6: 1166.85
A7: FY2026 | B7: 13357.17 | C7: 4239.56 | D7: 9117.61 | E7: 1340.87 | F7: 2569.22 | G7: 192.83 | H7: =SUM(I7,J7) -> 8047.93 | I7: 7603.77 | J7: 444.16

Sheet Nestle_CashFlow
A1: Financial Year | B1: Operating Cash Flow | C1: Investing Cash Flow | D1: Financing Cash Flow | E1: Capital Expenditure | F1: Free Cash Flow
A2: FY2021 | B2: 2062 | C2: -1920 | D2: -2019 | E2: -735 | F2: -1877
A3: FY2022 | B3: 2707 | C3: -393 | D3: -2123 | E3: -550 | F3: 191
A4: FY2023 | B4: 3456 | C4: -926 | D4: -2436 | E4: -1371 | F4: 94
A5: FY2024 | B5: 3925 | C5: -1238 | D5: -3135 | E5: -1883 | F5: -448
A6: FY2025 | B6: 2188 | C6: -1811 | D6: -1847 | E6: -2009 | F6: -1470
A7: FY2026 | B7: 5841 | C7: -625 | D7: -3179 | E7: -830 | F7: 2037

Sheet Ratios
A1: Company | B1: Financial Year | C1: Current Ratio | D1: Quick Ratio | E1: Debt to Equity | F1: ROA | G1: ROE | H1: Gross Margin | I1: Net Profit Margin | J1: Asset Turnover | K1: Interest Coverage | L1: EPS | M1: Dividend Yield
A2: HUL | B2: FY2021 | C2: 1.2 | D2: 0.8 | E2: 0.02 | F2: 0.1 | G2: 0.16421949 | H2: 0.46200136 | I2: 0.16647529 | J2: 0.7 | K2: 90.188034 | L2: 1.8 | M2: 1.77
A3: HUL | B3: FY2022 | C3: 1.38 | D3: 0.89 | E3: 0.03 | F3: 0.1054 | G3: 0.17677993 | H3: 0.44579186 | I3: 0.16537009 | J3: 0.75 | K3: 111 | L3: 1.85 | M3: 1.82
A4: HUL | B4: FY2023 | C4: 1.41 | D4: 0.92 | E4: 0.03 | F4: 0.113 | G4: 0.19272821 | H4: 0.41596236 | I4: 0.16003632 | J4: 0.84 | K4: 114.12281 | L4: 1.68 | M4: 1.65
A5: HUL | B5: FY2024 | C5: 1.66 | D5: 1.18 | E5: 0.03 | F5: 0.1106 | G5: 0.18479831 | H5: 0.45632997 | I5: 0.1529178 | J5: 0.82 | K5: 40.248503 | L5: 1.93 | M5: 1.97
A6: HUL | B6: FY2025 | C6: 1.33 | D6: 0.93 | E6: 0.03 | F6: 0.1059 | G6: 0.18857536 | H6: 0.45344704 | I6: 0.15190451 | J6: 0.77 | K6: 35.288714 | L6: 2.01 | M6: 1.98
A7: HUL | B7: FY2026 | C7: 1.22 | D7: 0.7 | E7: 0.03 | F7: 0.1071 | G7: 0.20796487 | H7: 0.44726066 | I7: 0.15722529 | J7: 0.81 | K7: 33.429268 | L7: 3.12 | M7: 2.02
A8: Nestle India | B8: FY2021 | C8: 1 | D8: 0.5 | E8: 0.1 | F8: 23.92 | G8: 1.1461225 | H8: 0.42192612 | I8: 0.15133655 | J8: 2 | K8: 15.724812 | L8: 1.2 | M8: 1
A9: Nestle India | B9: FY2022 | C9: 1.13 | D9: 0.45 | E9: 0.11 | F9: 26.75 | G9: 0.92846774 | H9: 0.39505686 | I9: 0.13512845 | J9: 1.92 | K9: 21.370771 | L9: 1.26 | M9: 1.17
A10: Nestle India | B10: FY2023 | C10: 0.95 | D10: 0.37 | E10: 0.11 | F10: 25.5 | G10: 1.1724159 | H10: 0.46242138 | I10: 0.15074374 | J10: 2.01 | K10: 33.884483 | L10: 1.17 | M10: 0.96
A11: Nestle India | B11: FY2024 | C11: 0.88 | D11: 0.29 | E11: 0.1 | F11: 0 | G11: 1.1295942 | H11: 0.4219159 | I11: 0.15470472 | J11: 0 | K11: 36.259331 | L11: 1.26 | M11: 1.01
A12: Nestle India | B12: FY2025 | C12: 0.8 | D12: 0.1 | E12: 0.29 | F12: 23.12 | G12: 0.71953657 | H12: 0.42119024 | I12: 0.14664412 | J12: 1.77 | K12: 31.113309 | L12: 1.48 | M12: 1.22
A13: Nestle India | B13: FY2026 | C13: 0.96 | D13: 0.35 | E13: 0.09 | F13: 22.58 | G13: 0.63744905 | H13: 0.41144999 | I13: 0.14616405 | J13: 1.82 | K13: 29.105742 | L13: 1.54 | M13: 1.03

Sheet Combined_Data
A1: Company | B1: Financial Year | C1: Revenue | D1: Gross Profit | E1: EBITDA | F1: Net Profit | G1: Total Assets | H1: Equity | I1: Total Debt | J1: Current Ratio | K1: ROE | L1: ROA | M1: Operating Cash Flow | N1: Free Cash Flow | O1: EPS
A2: HUL | B2: FY2021 | C2: =HUL_Financials!B2 -> 47028 | D2: =HUL_Financials!D2 -> 21727 | E2: =HUL_Financials!E2 -> 11626 | F2: =HUL_Financials!G2 -> 7829 | G2: =HUL_BalanceSheet!B2 -> 68740 | H2: =HUL_BalanceSheet!G2 -> 235 | I2: =HUL_BalanceSheet!H2 -> 21066 | J2: =Ratios!C2 -> 1.2 | K2: =Ratios!G2 -> 0.16421949 | L2: =Ratios!F2 -> 0.1 | M2: =HUL_CashFlow!B2 -> 8040 | N2: =HUL_CashFlow!F2 -> 3012 | O2: =Ratios!L2 -> 1.8
A3: HUL | B3: FY2022 | C3: =HUL_Financials!B3 -> 52446 | D3: =HUL_Financials!D3 -> 23380 | E3: =HUL_Financials!E3 -> 12857 | F3: =HUL_Financials!G3 -> 8673 | G3: =HUL_BalanceSheet!B3 -> 70506 | H3: =HUL_BalanceSheet!G3 -> 235 | I3: =HUL_BalanceSheet!H3 -> 21445 | J3: =Ratios!C3 -> 1.38 | K3: =Ratios!G3 -> 0.17677993 | L3: =Ratios!F3 -> 0.1054 | M3: =HUL_CashFlow!B3 -> 9063 | N3: =HUL_CashFlow!F3 -> -1474 | O3: =Ratios!L3 -> 1.85
A4: HUL | B4: FY2023 | C4: =HUL_Financials!B4 -> 60580 | D4: =HUL_Financials!D4 -> 25199 | E4: =HUL_Financials!E4 -> 14147 | F4: =HUL_Financials!G4 -> 9695 | G4: =HUL_BalanceSheet!B4 -> 73077 | H4: =HUL_BalanceSheet!G4 -> 235 | I4: =HUL_BalanceSheet!H4 -> 22773 | J4: =Ratios!C4 -> 1.41 | K4: =Ratios!G4 -> 0.19272821 | L4: =Ratios!F4 -> 0.113 | M4: =HUL_CashFlow!B4 -> 8045 | N4: =HUL_CashFlow!F4 -> -1698 | O4: =Ratios!L4 -> 1.68
A5: HUL | B5: FY2024 | C5: =HUL_Financials!B5 -> 61896 | D5: =HUL_Financials!D5 -> 28245 | E5: =HUL_Financials!E5 -> 14659 | F5: =HUL_Financials!G5 -> 9465 | G5: =HUL_BalanceSheet!B5 -> 78489 | H5: =HUL_BalanceSheet!G5 -> 235 | I5: =HUL_BalanceSheet!H5 -> 27271 | J5: =Ratios!C5 -> 1.66 | K5: =Ratios!G5 -> 0.18479831 | L5: =Ratios!F5 -> 0.1106 | M5: =HUL_CashFlow!B5 -> 9031 | N5: =HUL_CashFlow!F5 -> -1406 | O5: =Ratios!L5 -> 1.93
A6: HUL | B6: FY2025 | C6: =HUL_Financials!B6 -> 61328 | D6: =HUL_Financials!D6 -> 27809 | E6: =HUL_Financials!E6 -> 14698 | F6: =HUL_Financials!G6 -> 9316 | G6: =HUL_BalanceSheet!B6 -> 79863 | H6: =HUL_BalanceSheet!G6 -> 235 | I6: =HUL_BalanceSheet!H6 -> 30461 | J6: =Ratios!C6 -> 1.33 | K6: =Ratios!G6 -> 0.18857536 | L6: =Ratios!F6 -> 0.1059 | M6: =HUL_CashFlow!B6 -> 16782 | N6: =HUL_CashFlow!F6 -> 1424 | O6: =Ratios!L6 -> 2.01
A7: HUL | B7: FY2026 | C7: =HUL_Financials!B7 -> 64468 | D7: =HUL_Financials!D7 -> 28834 | E7: =HUL_Financials!E7 -> 15039 | F7: =HUL_Financials!G7 -> 10136 | G7: =HUL_BalanceSheet!B7 -> 79738 | H7: =HUL_BalanceSheet!G7 -> 235 | I7: =HUL_BalanceSheet!H7 -> 30999 | J7: =Ratios!C7 -> 1.22 | K7: =Ratios!G7 -> 0.20796487 | L7: =Ratios!F7 -> 0.1071 | M7: =HUL_CashFlow!B7 -> 11098 | N7: =HUL_CashFlow!F7 -> 4470 | O7: =Ratios!L7 -> 3.12
A8: Nestle India | B8: FY2021 | C8: =Nestle_Financials!B2 -> 14740.59 | D8: =Nestle_Financials!D2 -> 6219.44 | E8: =Nestle_Financials!E2 -> 3562.4 | F8: =Nestle_Financials!G2 -> 2230.79 | G8: =Nestle_BalanceSheet!B2 -> 8234.13 | H8: =Nestle_BalanceSheet!G2 -> 96.42 | I8: =Nestle_BalanceSheet!H2 -> 6287.75 | J8: =Ratios!C8 -> 1 | K8: =Ratios!G8 -> 1.1461225 | L8: =Ratios!F8 -> 23.92 | M8: =Nestle_CashFlow!B2 -> 2062 | N8: =Nestle_CashFlow!F2 -> -1877 | O8: =Ratios!L8 -> 1.2
A9: Nestle India | B9: FY2022 | C9: =Nestle_Financials!B3 -> 16896.96 | D9: =Nestle_Financials!D3 -> 6675.26 | E9: =Nestle_Financials!E3 -> 3706.29 | F9: =Nestle_Financials!G3 -> 2283.26 | G9: =Nestle_BalanceSheet!B3 -> 8978.74 | H9: =Nestle_BalanceSheet!G3 -> 96.42 | I9: =Nestle_BalanceSheet!H3 -> 6519.57 | J9: =Ratios!C9 -> 1.13 | K9: =Ratios!G9 -> 0.92846774 | L9: =Ratios!F9 -> 26.75 | M9: =Nestle_CashFlow!B3 -> 2707 | N9: =Nestle_CashFlow!F3 -> 191 | O9: =Ratios!L9 -> 1.26
A10: Nestle India | B10: FY2023 | C10: =Nestle_Financials!B4 -> 19126.3 | D10: =Nestle_Financials!D4 -> 8844.41 | E10: =Nestle_Financials!E4 -> 4470.99 | F10: =Nestle_Financials!G4 -> 2883.17 | G10: =Nestle_BalanceSheet!B4 -> 8978.74 | H10: =Nestle_BalanceSheet!G4 -> 96.42 | I10: =Nestle_BalanceSheet!H4 -> 6519.57 | J10: =Ratios!C10 -> 0.95 | K10: =Ratios!G10 -> 1.1724159 | L10: =Ratios!F10 -> 25.5 | M10: =Nestle_CashFlow!B4 -> 3456 | N10: =Nestle_CashFlow!F4 -> 94 | O10: =Ratios!L10 -> 1.17
A11: Nestle India | B11: FY2024 | C11: =Nestle_Financials!B5 -> 24393.89 | D11: =Nestle_Financials!D5 -> 10292.17 | E11: =Nestle_Financials!E5 -> 5843.12 | F11: =Nestle_Financials!G5 -> 3773.85 | G11: =Nestle_BalanceSheet!B5 -> 10523.06 | H11: =Nestle_BalanceSheet!G5 -> 96.42 | I11: =Nestle_BalanceSheet!H5 -> 7182.17 | J11: =Ratios!C11 -> 0.88 | K11: =Ratios!G11 -> 1.1295942 | L11: =Ratios!F11 -> 0 | M11: =Nestle_CashFlow!B5 -> 3925 | N11: =Nestle_CashFlow!F5 -> -448 | O11: =Ratios!L11 -> 1.26
A12: Nestle India | B12: FY2025 | C12: =Nestle_Financials!B6 -> 20201.56 | D12: =Nestle_Financials!D6 -> 8508.7 | E12: =Nestle_Financials!E6 -> 4771.33 | F12: =Nestle_Financials!G6 -> 2962.44 | G12: =Nestle_BalanceSheet!B6 -> 12323.89 | H12: =Nestle_BalanceSheet!G6 -> 96.42 | I12: =Nestle_BalanceSheet!H6 -> 8206.74 | J12: =Ratios!C12 -> 0.8 | K12: =Ratios!G12 -> 0.71953657 | L12: =Ratios!F12 -> 23.12 | M12: =Nestle_CashFlow!B6 -> 2188 | N12: =Nestle_CashFlow!F6 -> -1470 | O12: =Ratios!L12 -> 1.48
A13: Nestle India | B13: FY2026 | C13: =Nestle_Financials!B7 -> 23154.6 | D13: =Nestle_Financials!D7 -> 9526.96 | E13: =Nestle_Financials!E7 -> 5306.96 | F13: =Nestle_Financials!G7 -> 3384.37 | G13: =Nestle_BalanceSheet!B7 -> 13357.17 | H13: =Nestle_BalanceSheet!G7 -> 192.83 | I13: =Nestle_BalanceSheet!H7 -> 8047.93 | J13: =Ratios!C13 -> 0.96 | K13: =Ratios!G13 -> 0.63744905 | L13: =Ratios!F13 -> 22.58 | M13: =Nestle_CashFlow!B7 -> 5841 | N13: =Nestle_CashFlow!F7 -> 2037 | O13: =Ratios!L13 -> 1.54
